requests_mauth/__init__.py
requests_mauth/client.py
requests_mauth/rsa_sign.py
requests_mauth-1.1.0.dist-info/LICENSE.txt
requests_mauth-1.1.0.dist-info/METADATA
requests_mauth-1.1.0.dist-info/WHEEL
requests_mauth-1.1.0.dist-info/top_level.txt
requests_mauth-1.1.0.dist-info/RECORD
